<?xml version="1.0" encoding="UTF-8"?>
<objects serializationModel="Studio.02.01.00">
	<object class="AudioFile" id="{d9d8499c-3838-40ee-b61e-5f213c1492d5}">
		<property name="assetPath">
			<value>hitEnemy2.wav</value>
		</property>
		<property name="frequencyInKHz">
			<value>48</value>
		</property>
		<property name="channelCount">
			<value>2</value>
		</property>
		<property name="length">
			<value>2.3429791666666668</value>
		</property>
		<relationship name="masterAssetFolder">
			<destination>{e5a2c744-17dc-4adc-9e14-5a1face78599}</destination>
		</relationship>
	</object>
</objects>
